rock_physics_open/__init__.py
rock_physics_open/py.typed
rock_physics_open/version.py
rock_physics_open/equinor_utilities/__init__.py
rock_physics_open/equinor_utilities/anisotropy.py
rock_physics_open/equinor_utilities/conversions.py
rock_physics_open/equinor_utilities/classification_functions/__init__.py
rock_physics_open/equinor_utilities/classification_functions/class_stats.py
rock_physics_open/equinor_utilities/classification_functions/lin_class.py
rock_physics_open/equinor_utilities/classification_functions/mahal_class.py
rock_physics_open/equinor_utilities/classification_functions/norm_class.py
rock_physics_open/equinor_utilities/classification_functions/poly_class.py
rock_physics_open/equinor_utilities/classification_functions/post_prob.py
rock_physics_open/equinor_utilities/classification_functions/two_step_classification.py
rock_physics_open/equinor_utilities/gen_utilities/__init__.py
rock_physics_open/equinor_utilities/gen_utilities/dict_to_float.py
rock_physics_open/equinor_utilities/gen_utilities/dim_check_vector.py
rock_physics_open/equinor_utilities/gen_utilities/filter_input.py
rock_physics_open/equinor_utilities/gen_utilities/filter_output.py
rock_physics_open/equinor_utilities/machine_learning_utilities/__init__.py
rock_physics_open/equinor_utilities/machine_learning_utilities/base_pressure_model.py
rock_physics_open/equinor_utilities/machine_learning_utilities/dummy_vars.py
rock_physics_open/equinor_utilities/machine_learning_utilities/exponential_model.py
rock_physics_open/equinor_utilities/machine_learning_utilities/import_ml_models.py
rock_physics_open/equinor_utilities/machine_learning_utilities/polynomial_model.py
rock_physics_open/equinor_utilities/machine_learning_utilities/run_regression.py
rock_physics_open/equinor_utilities/machine_learning_utilities/sigmoidal_model.py
rock_physics_open/equinor_utilities/optimisation_utilities/__init__.py
rock_physics_open/equinor_utilities/optimisation_utilities/opt_subst_utilities.py
rock_physics_open-0.4.0.dist-info/licenses/LICENSE
rock_physics_open-0.4.0.dist-info/METADATA
rock_physics_open-0.4.0.dist-info/WHEEL
rock_physics_open-0.4.0.dist-info/top_level.txt
rock_physics_open-0.4.0.dist-info/RECORD
