Metadata-Version: 2.4
Name: rock_physics_open
Version: 0.4.0
Summary: Equinor Rock Physics Module
Author-email: Harald Flesche <hfle@equinor.com>, Eivind Jahren <ejah@equinor.com>, Jimmy Zurcher <jiz@equinor.com>
Maintainer-email: Harald Flesche <hfle@equinor.com>, Eirik Ola Aksnes <eoaksnes@equinor.com>, Sivert Utne <sutn@equinor.com>, Einar Wigum Arbo <earb@equinor.com>
Project-URL: Repository, https://github.com/equinor/rock-physics-open
Project-URL: Homepage, https://github.com/equinor/rock-physics-open
Project-URL: Changelog, https://github.com/equinor/rock-physics-open/blob/main/CHANGELOG.md
Keywords: energy,subsurface,seismic,rock physics,scientific,engineering
Classifier: Intended Audience :: Science/Research
Classifier: Topic :: Scientific/Engineering
Classifier: Topic :: Scientific/Engineering :: Physics
Classifier: Topic :: Software Development :: Libraries
Classifier: Topic :: Utilities
Classifier: Operating System :: POSIX :: Linux
Classifier: Programming Language :: Python :: 3.11
Classifier: Programming Language :: Python :: 3.12
Classifier: Programming Language :: Python :: 3.13
Classifier: Natural Language :: English
Requires-Python: >=3.11
License-File: LICENSE
Requires-Dist: numpy>=1.26.4
Requires-Dist: pandas>=2.0.2
Requires-Dist: matplotlib>=3.7.1
Requires-Dist: scipy<2,>=1.16.3
Requires-Dist: scikit-learn>=1.2.2
Requires-Dist: sympy>=1.13.3
Requires-Dist: tmatrix~=1.1.0
Requires-Dist: typing-extensions>=4.15.0
Dynamic: license-file
